kumosdk/__init__.py
kumosdk/vega/__init__.py
kumosdk/vega/alias.py
kumosdk/vega/aliases.py
kumosdk/vega/analytics.py
kumosdk/vega/analytics_rule.py
kumosdk/vega/analytics_rules.py
kumosdk/vega/api_call.py
kumosdk/vega/client.py
kumosdk/vega/collection.py
kumosdk/vega/collections.py
kumosdk/vega/configuration.py
kumosdk/vega/conversation_model.py
kumosdk/vega/conversations_models.py
kumosdk/vega/debug.py
kumosdk/vega/document.py
kumosdk/vega/documents.py
kumosdk/vega/exceptions.py
kumosdk/vega/key.py
kumosdk/vega/keys.py
kumosdk/vega/logger.py
kumosdk/vega/multi_search.py
kumosdk/vega/operations.py
kumosdk/vega/override.py
kumosdk/vega/overrides.py
kumosdk/vega/preprocess.py
kumosdk/vega/stopwords.py
kumosdk/vega/stopwords_set.py
kumosdk/vega/synonym.py
kumosdk/vega/synonyms.py
kumosdk/vega/validation.py
kumosdk-0.3.2.dist-info/LICENSE
kumosdk-0.3.2.dist-info/METADATA
kumosdk-0.3.2.dist-info/WHEEL
kumosdk-0.3.2.dist-info/top_level.txt
kumosdk-0.3.2.dist-info/RECORD
