Metadata-Version: 2.1
Name: kumosdk
Version: 0.3.2
Summary: Python client for kumo search, AI infrastrure searching.
Author-email: Kumo <contact@vega.org>
License: GPL 3.0
Project-URL: Documentation, https://gitee.com/kumo-pub/kumosdk-py
Project-URL: Source, https://gitee.com/kumo-pub/kumosdk-py
Project-URL: Tracker, https://gitee.com/kumo-pub/kumosdk-py/issues
Keywords: search,AI,kumo
Classifier: Development Status :: 5 - Production/Stable
Classifier: Intended Audience :: Developers
Classifier: License :: OSI Approved :: Apache Software License
Classifier: Programming Language :: Python
Classifier: Programming Language :: Python :: 3
Requires-Python: >=3
License-File: LICENSE
Requires-Dist: requests
